setuptools_autometa.py
Setuptools_Autometa-0.1.1.post3.dist-info/entry_points.txt
Setuptools_Autometa-0.1.1.post3.dist-info/top_level.txt
Setuptools_Autometa-0.1.1.post3.dist-info/zip-safe
Setuptools_Autometa-0.1.1.post3.dist-info/METADATA
Setuptools_Autometa-0.1.1.post3.dist-info/DESCRIPTION.rst
Setuptools_Autometa-0.1.1.post3.dist-info/metadata.json
Setuptools_Autometa-0.1.1.post3.dist-info/WHEEL
Setuptools_Autometa-0.1.1.post3.dist-info/RECORD
