Metadata-Version: 2.0
Name: Setuptools-Autometa
Version: 0.1.1.post3
Summary: Add autometa keyword to the setuptools.setup function which automatically fills version, description and long_description keywords
Home-page: https://przybys.eu/software/setuptools-autometa
Author: Michał Przybyś
Author-email: michal@przybys.eu
License: BSD
Keywords: automatic,description,setuptools,version
Platform: UNKNOWN
Classifier: Development Status :: 5 - Production/Stable
Classifier: Environment :: Plugins
Classifier: Framework :: Setuptools Plugin
Classifier: Intended Audience :: Developers
Classifier: Intended Audience :: Other Audience
Classifier: License :: OSI Approved :: BSD License
Classifier: Natural Language :: English
Classifier: Operating System :: OS Independent
Classifier: Programming Language :: Python :: 2
Classifier: Programming Language :: Python :: 3
Classifier: Topic :: Software Development
